spark_map/__init__.py
spark_map/functions.py
spark_map/mapping.py
spark_map/utils.py
spark_map-0.2.78.dist-info/LICENSE.txt
spark_map-0.2.78.dist-info/METADATA
spark_map-0.2.78.dist-info/WHEEL
spark_map-0.2.78.dist-info/top_level.txt
spark_map-0.2.78.dist-info/RECORD
