Metadata-Version: 2.1
Name: spark-map
Version: 0.2.78
Summary: Pyspark implementation of `map()` function for spark DataFrames
Author-email: Pedro Faria <pedropark99@gmail.com>
License: Copyright 2022 Pedro Duarte Faria
Project-URL: Homepage, https://pedropark99.github.io/spark_map/
Project-URL: Repo, https://github.com/pedropark99/spark_map
Project-URL: Issues, https://github.com/pedropark99/spark_map/issues
Classifier: Programming Language :: Python :: 3
Classifier: License :: OSI Approved :: MIT License
Classifier: Operating System :: OS Independent
Requires-Python: >=3.7
License-File: LICENSE.txt
Requires-Dist: pyspark
Requires-Dist: setuptools
Requires-Dist: toml
